trifinger_simulation/__init__.py
trifinger_simulation/action.py
trifinger_simulation/camera.py
trifinger_simulation/collision_objects.py
trifinger_simulation/finger_types_data.py
trifinger_simulation/observation.py
trifinger_simulation/pinocchio_utils.py
trifinger_simulation/py.typed
trifinger_simulation/real_finger.py
trifinger_simulation/sample.py
trifinger_simulation/sim_finger.py
trifinger_simulation/trifinger_platform.py
trifinger_simulation/trifingerpro_limits.py
trifinger_simulation/visual_objects.py
trifinger_simulation/data/camera_params/camera180_cropped.yml
trifinger_simulation/data/camera_params/camera180_cropped_and_downsampled.yml
trifinger_simulation/data/camera_params/camera180_full.yml
trifinger_simulation/data/camera_params/camera300_cropped.yml
trifinger_simulation/data/camera_params/camera300_cropped_and_downsampled.yml
trifinger_simulation/data/camera_params/camera300_full.yml
trifinger_simulation/data/camera_params/camera60_cropped.yml
trifinger_simulation/data/camera_params/camera60_cropped_and_downsampled.yml
trifinger_simulation/data/camera_params/camera60_full.yml
trifinger_simulation/data/cube_v2/cube_v2.blend
trifinger_simulation/data/cube_v2/cube_v2.mtl
trifinger_simulation/data/cube_v2/cube_v2.obj
trifinger_simulation/data/cube_v2/cube_v2.urdf
trifinger_simulation/data/cube_v2/cube_v2_texture.png
trifinger_simulation/gym_wrapper/__init__.py
trifinger_simulation/gym_wrapper/data_logger.py
trifinger_simulation/gym_wrapper/finger_spaces.py
trifinger_simulation/gym_wrapper/utils.py
trifinger_simulation/gym_wrapper/envs/__init__.py
trifinger_simulation/gym_wrapper/envs/cube_env.py
trifinger_simulation/gym_wrapper/envs/cube_trajectory_env.py
trifinger_simulation/gym_wrapper/envs/trifinger_push.py
trifinger_simulation/gym_wrapper/envs/trifinger_reach.py
trifinger_simulation/tasks/__init__.py
trifinger_simulation/tasks/move_cuboid.py
trifinger_simulation/tasks/move_cube/__init__.py
trifinger_simulation/tasks/move_cube/__main__.py
trifinger_simulation-2.0.0.dist-info/LICENSE
trifinger_simulation-2.0.0.dist-info/METADATA
trifinger_simulation-2.0.0.dist-info/WHEEL
trifinger_simulation-2.0.0.dist-info/top_level.txt
trifinger_simulation-2.0.0.dist-info/RECORD
