Metadata-Version: 2.1
Name: trifinger_simulation
Version: 2.0.0
Summary: TriFinger Robot Simulation
Home-page: https://open-dynamic-robot-initiative.github.io/trifinger_simulation
Author: Felix Widmaier
Author-email: felix.widmaier@tue.mpg.de
License: BSD 3-Clause License
Project-URL: Documentation, https://open-dynamic-robot-initiative.github.io/trifinger_simulation
Project-URL: Source Code, https://github.com/open-dynamic-robot-initiative/trifinger_simulation
Project-URL: Bug Tracker, https://github.com/open-dynamic-robot-initiative/trifinger_simulation/issues
Keywords: TriFinger,Simulation,Robotics,Robot
Classifier: Development Status :: 5 - Production/Stable
Classifier: License :: OSI Approved :: BSD License
Classifier: Programming Language :: Python :: 3
Classifier: Topic :: Scientific/Engineering
License-File: LICENSE
Requires-Dist: numpy >=1.19.1
Requires-Dist: scipy >=1.5.4
Requires-Dist: pin >=2.4.7
Requires-Dist: pybullet >=3.0.8
Requires-Dist: gym >=0.23.1
Requires-Dist: opencv-python >=4.2.0.34
Requires-Dist: pyyaml >=5.3.1
Requires-Dist: robot-properties-fingers >=2.0.2
Provides-Extra: doc
Requires-Dist: sphinx ; extra == 'doc'
Requires-Dist: sphinx-rtd-theme ; extra == 'doc'
Provides-Extra: mypy
Requires-Dist: mypy ; extra == 'mypy'
Requires-Dist: types-PyYAML ; extra == 'mypy'
Requires-Dist: types-setuptools ; extra == 'mypy'
Provides-Extra: test
Requires-Dist: pytest ; extra == 'test'
